kitchenware/__init__.py
kitchenware/data_encoding.py
kitchenware/data_io.py
kitchenware/dtype.py
kitchenware/geometry.py
kitchenware/maps.py
kitchenware/metrics.py
kitchenware/standard_encoding.py
kitchenware/standard_template.py
kitchenware/structure.py
kitchenware/structure_io.py
kitchenware-0.3.0.dist-info/licenses/LICENSE
kitchenware-0.3.0.dist-info/METADATA
kitchenware-0.3.0.dist-info/WHEEL
kitchenware-0.3.0.dist-info/top_level.txt
kitchenware-0.3.0.dist-info/RECORD
