Metadata-Version: 2.4
Name: kitchenware
Version: 0.3.0
Summary: Utility tools to load and process biomolecular data.
Author-email: Lucien Krapp <lucienkrapp@gmail.com>
Project-URL: Homepage, https://github.com/lfkrapp/kitchenware
Project-URL: Issues, https://github.com/lfkrapp/kitchenware/issues
Requires-Python: >=3.12
License-File: LICENSE
Requires-Dist: gemmi>=0.7.0
Requires-Dist: mrcfile>=1.5.3
Requires-Dist: numpy>=2.2.1
Requires-Dist: torch>=2.5.1
Dynamic: license-file
